mudra_sdk/__init__.py
mudra_sdk/libs/__init__.py
mudra_sdk/libs/library_loader.py
mudra_sdk/libs/windows/x64/MudraSDK.dll
mudra_sdk/libs/windows/x86/MudraSDK.dll
mudra_sdk/models/__init__.py
mudra_sdk/models/callbacks.py
mudra_sdk/models/computation_wrapper.py
mudra_sdk/models/enums.py
mudra_sdk/models/firmware_status.py
mudra_sdk/models/mudra.py
mudra_sdk/models/mudra_device.py
mudra_sdk/service/__init__.py
mudra_sdk/service/ble_service.py
mudra_sdk_test_1-0.1.28.dist-info/METADATA
mudra_sdk_test_1-0.1.28.dist-info/WHEEL
mudra_sdk_test_1-0.1.28.dist-info/top_level.txt
mudra_sdk_test_1-0.1.28.dist-info/RECORD
