Metadata-Version: 2.4
Name: mudra_sdk_test_1
Version: 0.1.28
Summary: Mudra SDK
Author: Foad Khoury
Requires-Python: >=3.7
Requires-Dist: bleak>=0.21.0
Dynamic: author
Dynamic: requires-dist
Dynamic: requires-python
Dynamic: summary
